[
    {
        "id": 0,
        "timestamp": [
            0.31499999999999995,
            1.815
        ],
        "feature_shape": [
            47,
            39
        ]
    },
    {
        "id": 1,
        "timestamp": [
            0.81,
            2.31
        ],
        "feature_shape": [
            47,
            39
        ]
    },
    {
        "id": 2,
        "timestamp": [
            3.24,
            4.74
        ],
        "feature_shape": [
            47,
            39
        ]
    },
    {
        "id": 3,
        "timestamp": [
            8.37,
            9.87
        ],
        "feature_shape": [
            47,
            39
        ]
    },
    {
        "id": 4,
        "timestamp": [
            13.545,
            15.045
        ],
        "feature_shape": [
            47,
            39
        ]
    },
    {
        "id": 5,
        "timestamp": [
            16.335,
            17.835
        ],
        "feature_shape": [
            47,
            39
        ]
    },
    {
        "id": 6,
        "timestamp": [
            19.065,
            20.565
        ],
        "feature_shape": [
            47,
            39
        ]
    },
    {
        "id": 7,
        "timestamp": [
            29.49,
            30.99
        ],
        "feature_shape": [
            47,
            39
        ]
    },
    {
        "id": 8,
        "timestamp": [
            32.34,
            33.84
        ],
        "feature_shape": [
            47,
            39
        ]
    },
    {
        "id": 9,
        "timestamp": [
            43.08,
            44.58
        ],
        "feature_shape": [
            47,
            39
        ]
    },
    {
        "id": 10,
        "timestamp": [
            45.795,
            47.295
        ],
        "feature_shape": [
            47,
            39
        ]
    },
    {
        "id": 11,
        "timestamp": [
            51.045,
            52.545
        ],
        "feature_shape": [
            47,
            39
        ]
    },
    {
        "id": 12,
        "timestamp": [
            61.725,
            63.225
        ],
        "feature_shape": [
            47,
            39
        ]
    },
    {
        "id": 13,
        "timestamp": [
            64.26,
            65.76
        ],
        "feature_shape": [
            47,
            39
        ]
    },
    {
        "id": 14,
        "timestamp": [
            72.15,
            73.65
        ],
        "feature_shape": [
            47,
            39
        ]
    },
    {
        "id": 15,
        "timestamp": [
            96.465,
            97.965
        ],
        "feature_shape": [
            47,
            39
        ]
    },
    {
        "id": 16,
        "timestamp": [
            109.95,
            111.45
        ],
        "feature_shape": [
            47,
            39
        ]
    },
    {
        "id": 17,
        "timestamp": [
            117.975,
            119.475
        ],
        "feature_shape": [
            47,
            39
        ]
    },
    {
        "id": 18,
        "timestamp": [
            120.72,
            122.22
        ],
        "feature_shape": [
            47,
            39
        ]
    },
    {
        "id": 19,
        "timestamp": [
            126.255,
            127.755
        ],
        "feature_shape": [
            47,
            39
        ]
    },
    {
        "id": 20,
        "timestamp": [
            139.905,
            141.405
        ],
        "feature_shape": [
            47,
            39
        ]
    }
]