[
    {
        "id": 0,
        "timestamp": [
            2.085,
            3.585
        ],
        "feature_shape": [
            47,
            39
        ]
    },
    {
        "id": 1,
        "timestamp": [
            4.47,
            5.97
        ],
        "feature_shape": [
            47,
            39
        ]
    },
    {
        "id": 2,
        "timestamp": [
            6.87,
            8.370000000000001
        ],
        "feature_shape": [
            47,
            39
        ]
    },
    {
        "id": 3,
        "timestamp": [
            9.135,
            10.635
        ],
        "feature_shape": [
            47,
            39
        ]
    },
    {
        "id": 4,
        "timestamp": [
            11.415,
            12.915
        ],
        "feature_shape": [
            47,
            39
        ]
    },
    {
        "id": 5,
        "timestamp": [
            13.68,
            15.18
        ],
        "feature_shape": [
            47,
            39
        ]
    },
    {
        "id": 6,
        "timestamp": [
            15.855,
            17.355
        ],
        "feature_shape": [
            47,
            39
        ]
    },
    {
        "id": 7,
        "timestamp": [
            18.0,
            19.5
        ],
        "feature_shape": [
            47,
            39
        ]
    },
    {
        "id": 8,
        "timestamp": [
            20.37,
            21.87
        ],
        "feature_shape": [
            47,
            39
        ]
    },
    {
        "id": 9,
        "timestamp": [
            22.8,
            24.3
        ],
        "feature_shape": [
            47,
            39
        ]
    },
    {
        "id": 10,
        "timestamp": [
            25.26,
            26.76
        ],
        "feature_shape": [
            47,
            39
        ]
    },
    {
        "id": 11,
        "timestamp": [
            27.96,
            29.46
        ],
        "feature_shape": [
            47,
            39
        ]
    },
    {
        "id": 12,
        "timestamp": [
            30.42,
            31.92
        ],
        "feature_shape": [
            47,
            39
        ]
    },
    {
        "id": 13,
        "timestamp": [
            32.91,
            34.41
        ],
        "feature_shape": [
            47,
            39
        ]
    },
    {
        "id": 14,
        "timestamp": [
            35.25,
            36.75
        ],
        "feature_shape": [
            47,
            39
        ]
    },
    {
        "id": 15,
        "timestamp": [
            37.68,
            39.18
        ],
        "feature_shape": [
            47,
            39
        ]
    },
    {
        "id": 16,
        "timestamp": [
            39.99,
            41.49
        ],
        "feature_shape": [
            47,
            39
        ]
    },
    {
        "id": 17,
        "timestamp": [
            42.525,
            44.025
        ],
        "feature_shape": [
            47,
            39
        ]
    },
    {
        "id": 18,
        "timestamp": [
            45.18,
            46.68
        ],
        "feature_shape": [
            47,
            39
        ]
    },
    {
        "id": 19,
        "timestamp": [
            47.415,
            48.915
        ],
        "feature_shape": [
            47,
            39
        ]
    },
    {
        "id": 20,
        "timestamp": [
            49.695,
            51.195
        ],
        "feature_shape": [
            47,
            39
        ]
    },
    {
        "id": 21,
        "timestamp": [
            52.335,
            53.835
        ],
        "feature_shape": [
            47,
            39
        ]
    },
    {
        "id": 22,
        "timestamp": [
            54.9,
            56.4
        ],
        "feature_shape": [
            47,
            39
        ]
    },
    {
        "id": 23,
        "timestamp": [
            57.48,
            58.98
        ],
        "feature_shape": [
            47,
            39
        ]
    },
    {
        "id": 24,
        "timestamp": [
            60.09,
            61.59
        ],
        "feature_shape": [
            47,
            39
        ]
    },
    {
        "id": 25,
        "timestamp": [
            62.7,
            64.2
        ],
        "feature_shape": [
            47,
            39
        ]
    },
    {
        "id": 26,
        "timestamp": [
            65.31,
            66.81
        ],
        "feature_shape": [
            47,
            39
        ]
    },
    {
        "id": 27,
        "timestamp": [
            67.905,
            69.405
        ],
        "feature_shape": [
            47,
            39
        ]
    },
    {
        "id": 28,
        "timestamp": [
            70.23,
            71.73
        ],
        "feature_shape": [
            47,
            39
        ]
    },
    {
        "id": 29,
        "timestamp": [
            72.72,
            74.22
        ],
        "feature_shape": [
            47,
            39
        ]
    },
    {
        "id": 30,
        "timestamp": [
            75.405,
            76.905
        ],
        "feature_shape": [
            47,
            39
        ]
    },
    {
        "id": 31,
        "timestamp": [
            78.315,
            79.815
        ],
        "feature_shape": [
            47,
            39
        ]
    },
    {
        "id": 32,
        "timestamp": [
            80.925,
            82.425
        ],
        "feature_shape": [
            47,
            39
        ]
    },
    {
        "id": 33,
        "timestamp": [
            83.52,
            85.02
        ],
        "feature_shape": [
            47,
            39
        ]
    },
    {
        "id": 34,
        "timestamp": [
            86.07,
            87.57
        ],
        "feature_shape": [
            47,
            39
        ]
    },
    {
        "id": 35,
        "timestamp": [
            88.83,
            90.33
        ],
        "feature_shape": [
            47,
            39
        ]
    },
    {
        "id": 36,
        "timestamp": [
            91.395,
            92.895
        ],
        "feature_shape": [
            47,
            39
        ]
    },
    {
        "id": 37,
        "timestamp": [
            93.975,
            95.475
        ],
        "feature_shape": [
            47,
            39
        ]
    },
    {
        "id": 38,
        "timestamp": [
            96.885,
            98.385
        ],
        "feature_shape": [
            47,
            39
        ]
    },
    {
        "id": 39,
        "timestamp": [
            99.6,
            101.1
        ],
        "feature_shape": [
            47,
            39
        ]
    },
    {
        "id": 40,
        "timestamp": [
            102.345,
            103.845
        ],
        "feature_shape": [
            47,
            39
        ]
    },
    {
        "id": 41,
        "timestamp": [
            105.24,
            106.74
        ],
        "feature_shape": [
            47,
            39
        ]
    },
    {
        "id": 42,
        "timestamp": [
            108.195,
            109.695
        ],
        "feature_shape": [
            47,
            39
        ]
    },
    {
        "id": 43,
        "timestamp": [
            111.045,
            112.545
        ],
        "feature_shape": [
            47,
            39
        ]
    },
    {
        "id": 44,
        "timestamp": [
            113.955,
            115.455
        ],
        "feature_shape": [
            47,
            39
        ]
    },
    {
        "id": 45,
        "timestamp": [
            116.925,
            118.425
        ],
        "feature_shape": [
            47,
            39
        ]
    },
    {
        "id": 46,
        "timestamp": [
            119.82,
            121.32
        ],
        "feature_shape": [
            47,
            39
        ]
    },
    {
        "id": 47,
        "timestamp": [
            122.565,
            124.065
        ],
        "feature_shape": [
            47,
            39
        ]
    },
    {
        "id": 48,
        "timestamp": [
            125.295,
            126.795
        ],
        "feature_shape": [
            47,
            39
        ]
    },
    {
        "id": 49,
        "timestamp": [
            128.145,
            129.645
        ],
        "feature_shape": [
            47,
            39
        ]
    },
    {
        "id": 50,
        "timestamp": [
            131.04,
            132.54
        ],
        "feature_shape": [
            47,
            39
        ]
    },
    {
        "id": 51,
        "timestamp": [
            133.815,
            135.315
        ],
        "feature_shape": [
            47,
            39
        ]
    },
    {
        "id": 52,
        "timestamp": [
            136.47,
            137.97
        ],
        "feature_shape": [
            47,
            39
        ]
    },
    {
        "id": 53,
        "timestamp": [
            139.395,
            140.895
        ],
        "feature_shape": [
            47,
            39
        ]
    },
    {
        "id": 54,
        "timestamp": [
            142.23,
            143.73
        ],
        "feature_shape": [
            47,
            39
        ]
    },
    {
        "id": 55,
        "timestamp": [
            145.125,
            146.625
        ],
        "feature_shape": [
            47,
            39
        ]
    },
    {
        "id": 56,
        "timestamp": [
            148.005,
            149.505
        ],
        "feature_shape": [
            47,
            39
        ]
    },
    {
        "id": 57,
        "timestamp": [
            150.885,
            152.385
        ],
        "feature_shape": [
            47,
            39
        ]
    },
    {
        "id": 58,
        "timestamp": [
            153.765,
            155.265
        ],
        "feature_shape": [
            47,
            39
        ]
    }
]