[
  {
    "id": 0,
    "abs_timestamp": [
      12.795,
      14.295
    ],
    "text": "選擇",
    "pinyin": "xuǎn zé"
  },
  {
    "id": 1,
    "abs_timestamp": [
      15.06,
      16.560000000000002
    ],
    "text": "選擇",
    "pinyin": "xuǎn zé"
  },
  {
    "id": 2,
    "abs_timestamp": [
      17.565,
      19.065
    ],
    "text": "选择",
    "pinyin": "xuǎn zé"
  },
  {
    "id": 3,
    "abs_timestamp": [
      20.16,
      21.66
    ],
    "text": "选择",
    "pinyin": "xuǎn zé"
  },
  {
    "id": 4,
    "abs_timestamp": [
      22.83,
      24.33
    ],
    "text": "选择",
    "pinyin": "xuǎn zé"
  },
  {
    "id": 5,
    "abs_timestamp": [
      25.47,
      26.97
    ],
    "text": "选择",
    "pinyin": "xuǎn zé"
  },
  {
    "id": 6,
    "abs_timestamp": [
      28.17,
      29.67
    ],
    "text": "選擇",
    "pinyin": "xuǎn zé"
  },
  {
    "id": 7,
    "abs_timestamp": [
      30.735,
      32.235
    ],
    "text": "選擇",
    "pinyin": "xuǎn zé"
  },
  {
    "id": 8,
    "abs_timestamp": [
      35.655,
      37.155
    ],
    "text": "選擇",
    "pinyin": "xuǎn zé"
  },
  {
    "id": 9,
    "abs_timestamp": [
      38.085,
      39.585
    ],
    "text": "選擇",
    "pinyin": "xuǎn zé"
  },
  {
    "id": 10,
    "abs_timestamp": [
      40.605,
      42.105
    ],
    "text": "選擇",
    "pinyin": "xuǎn zé"
  },
  {
    "id": 11,
    "abs_timestamp": [
      43.11,
      44.61
    ],
    "text": "選擇",
    "pinyin": "xuǎn zé"
  },
  {
    "id": 12,
    "abs_timestamp": [
      45.735,
      47.235
    ],
    "text": "选择",
    "pinyin": "xuǎn zé"
  },
  {
    "id": 13,
    "abs_timestamp": [
      48.285,
      49.785
    ],
    "text": "選擇",
    "pinyin": "xuǎn zé"
  },
  {
    "id": 14,
    "abs_timestamp": [
      51.045,
      52.545
    ],
    "text": "選擇",
    "pinyin": "xuǎn zé"
  },
  {
    "id": 15,
    "abs_timestamp": [
      53.58,
      55.08
    ],
    "text": "選擇",
    "pinyin": "xuǎn zé"
  },
  {
    "id": 16,
    "abs_timestamp": [
      60.525,
      62.025
    ],
    "text": "選擇",
    "pinyin": "xuǎn zé"
  },
  {
    "id": 17,
    "abs_timestamp": [
      62.925,
      64.425
    ],
    "text": "選擇",
    "pinyin": "xuǎn zé"
  },
  {
    "id": 18,
    "abs_timestamp": [
      65.415,
      66.915
    ],
    "text": "选择",
    "pinyin": "xuǎn zé"
  },
  {
    "id": 19,
    "abs_timestamp": [
      67.845,
      69.345
    ],
    "text": "選擇",
    "pinyin": "xuǎn zé"
  },
  {
    "id": 20,
    "abs_timestamp": [
      70.485,
      71.985
    ],
    "text": "选择",
    "pinyin": "xuǎn zé"
  },
  {
    "id": 21,
    "abs_timestamp": [
      73.11,
      74.61
    ],
    "text": "選擇",
    "pinyin": "xuǎn zé"
  },
  {
    "id": 22,
    "abs_timestamp": [
      75.945,
      77.445
    ],
    "text": "選擇",
    "pinyin": "xuǎn zé"
  },
  {
    "id": 23,
    "abs_timestamp": [
      78.27,
      79.77
    ],
    "text": "選擇",
    "pinyin": "xuǎn zé"
  },
  {
    "id": 24,
    "abs_timestamp": [
      81.285,
      82.785
    ],
    "text": "选择",
    "pinyin": "xuǎn zé"
  },
  {
    "id": 25,
    "abs_timestamp": [
      84.21,
      85.71
    ],
    "text": "选择",
    "pinyin": "xuǎn zé"
  },
  {
    "id": 26,
    "abs_timestamp": [
      86.985,
      88.485
    ],
    "text": "选择",
    "pinyin": "xuǎn zé"
  },
  {
    "id": 27,
    "abs_timestamp": [
      89.745,
      91.245
    ],
    "text": "选择",
    "pinyin": "xuǎn zé"
  },
  {
    "id": 28,
    "abs_timestamp": [
      93.24,
      94.74
    ],
    "text": "選擇",
    "pinyin": "xuǎn zé"
  },
  {
    "id": 29,
    "abs_timestamp": [
      95.745,
      97.245
    ],
    "text": "选择",
    "pinyin": "xuǎn zé"
  },
  {
    "id": 30,
    "abs_timestamp": [
      98.64,
      100.14
    ],
    "text": "选择",
    "pinyin": "xuǎn zé"
  },
  {
    "id": 31,
    "abs_timestamp": [
      101.205,
      102.705
    ],
    "text": "选择",
    "pinyin": "xuǎn zé"
  },
  {
    "id": 32,
    "abs_timestamp": [
      103.815,
      105.315
    ],
    "text": "选择",
    "pinyin": "xuǎn zé"
  },
  {
    "id": 33,
    "abs_timestamp": [
      106.155,
      107.655
    ],
    "text": "选择",
    "pinyin": "xuǎn zé"
  },
  {
    "id": 34,
    "abs_timestamp": [
      108.585,
      110.085
    ],
    "text": "選擇",
    "pinyin": "xuǎn zé"
  },
  {
    "id": 35,
    "abs_timestamp": [
      111.015,
      112.515
    ],
    "text": "選擇",
    "pinyin": "xuǎn zé"
  },
  {
    "id": 36,
    "abs_timestamp": [
      113.625,
      115.125
    ],
    "text": "选择",
    "pinyin": "xuǎn zé"
  },
  {
    "id": 37,
    "abs_timestamp": [
      116.085,
      117.585
    ],
    "text": "選擇",
    "pinyin": "xuǎn zé"
  },
  {
    "id": 38,
    "abs_timestamp": [
      118.755,
      120.255
    ],
    "text": "选择",
    "pinyin": "xuǎn zé"
  },
  {
    "id": 39,
    "abs_timestamp": [
      123.915,
      125.415
    ],
    "text": "選擇",
    "pinyin": "xuǎn zé"
  },
  {
    "id": 40,
    "abs_timestamp": [
      126.735,
      128.235
    ],
    "text": "選擇",
    "pinyin": "xuǎn zé"
  },
  {
    "id": 41,
    "abs_timestamp": [
      129.57,
      131.07
    ],
    "text": "選擇",
    "pinyin": "xuǎn zé"
  },
  {
    "id": 42,
    "abs_timestamp": [
      132.21,
      133.71
    ],
    "text": "選擇",
    "pinyin": "xuǎn zé"
  },
  {
    "id": 43,
    "abs_timestamp": [
      134.88,
      136.38
    ],
    "text": "選擇",
    "pinyin": "xuǎn zé"
  },
  {
    "id": 44,
    "abs_timestamp": [
      137.895,
      139.395
    ],
    "text": "选择",
    "pinyin": "xuǎn zé"
  },
  {
    "id": 45,
    "abs_timestamp": [
      143.565,
      145.065
    ],
    "text": "選擇",
    "pinyin": "xuǎn zé"
  },
  {
    "id": 46,
    "abs_timestamp": [
      146.16,
      147.66
    ],
    "text": "選擇",
    "pinyin": "xuǎn zé"
  },
  {
    "id": 47,
    "abs_timestamp": [
      148.695,
      150.195
    ],
    "text": "選擇",
    "pinyin": "xuǎn zé"
  },
  {
    "id": 48,
    "abs_timestamp": [
      151.14,
      152.64
    ],
    "text": "選擇",
    "pinyin": "xuǎn zé"
  },
  {
    "id": 49,
    "abs_timestamp": [
      153.945,
      155.445
    ],
    "text": "選擇",
    "pinyin": "xuǎn zé"
  },
  {
    "id": 50,
    "abs_timestamp": [
      156.48,
      157.98
    ],
    "text": "選擇",
    "pinyin": "xuǎn zé"
  },
  {
    "id": 51,
    "abs_timestamp": [
      159.3,
      160.8
    ],
    "text": "選擇",
    "pinyin": "xuǎn zé"
  },
  {
    "id": 52,
    "abs_timestamp": [
      161.685,
      163.185
    ],
    "text": "選擇",
    "pinyin": "xuǎn zé"
  },
  {
    "id": 53,
    "abs_timestamp": [
      164.04,
      165.54
    ],
    "text": "選擇",
    "pinyin": "xuǎn zé"
  }
]